{
  "game_id": 401585233,
  "fecha": "2026-02-14",
  "home_team": "Los Angeles Lakers",
  "away_team": "Portland Trail Blazers",
  "home_score": 110,
  "away_score": 134,
  "home_stats": {
    "PTS": 134,
    "REB": 45,
    "AST": 28,
    "STL": 12,
    "BLK": 9,
    "TO": 6,
    "PF": 10,
    "FG%": 54.7,
    "3P%": 39.4,
    "FT%": 93.1
  },
  "away_stats": {
    "PTS": 110,
    "REB": 35,
    "AST": 24,
    "STL": 12,
    "BLK": 7,
    "TO": 5,
    "PF": 10,
    "FG%": 46.7,
    "3P%": 31.0,
    "FT%": 85.0
  }
}