{
  "game_id": 401585275,
  "fecha": "2026-02-14",
  "home_team": "Charlotte Hornets",
  "away_team": "Utah Jazz",
  "home_score": 122,
  "away_score": 134,
  "home_stats": {
    "PTS": 122,
    "REB": 35,
    "AST": 35,
    "STL": 10,
    "BLK": 7,
    "TO": 6,
    "PF": 9,
    "FG%": 51.1,
    "3P%": 40.6,
    "FT%": 71.4
  },
  "away_stats": {
    "PTS": 134,
    "REB": 49,
    "AST": 38,
    "STL": 13,
    "BLK": 6,
    "TO": 6,
    "PF": 15,
    "FG%": 55.9,
    "3P%": 41.5,
    "FT%": 76.5
  }
}