{
  "game_id": 401585764,
  "fecha": "2026-02-14",
  "home_team": "Orlando Magic",
  "away_team": "Chicago Bulls",
  "home_score": 98,
  "away_score": 113,
  "home_stats": {
    "PTS": 113,
    "REB": 40,
    "AST": 24,
    "STL": 10,
    "BLK": 12,
    "TO": 4,
    "PF": 10,
    "FG%": 46.7,
    "3P%": 32.4,
    "FT%": 94.7
  },
  "away_stats": {
    "PTS": 98,
    "REB": 37,
    "AST": 20,
    "STL": 21,
    "BLK": 7,
    "TO": 5,
    "PF": 8,
    "FG%": 50.7,
    "3P%": 30.0,
    "FT%": 72.7
  }
}