{
  "game_id": 401617579,
  "fecha": "2026-02-14",
  "home_team": "Boston Celtics",
  "away_team": "New York Knicks",
  "home_score": 123,
  "away_score": 133,
  "home_stats": {
    "PTS": 133,
    "REB": 34,
    "AST": 24,
    "STL": 7,
    "BLK": 8,
    "TO": 5,
    "PF": 8,
    "FG%": 52.7,
    "3P%": 40.4,
    "FT%": 85.7
  },
  "away_stats": {
    "PTS": 123,
    "REB": 44,
    "AST": 28,
    "STL": 13,
    "BLK": 4,
    "TO": 3,
    "PF": 12,
    "FG%": 50.0,
    "3P%": 40.5,
    "FT%": 74.1
  }
}